rsacrack/__init__.py
rsacrack-1.0.1.dist-info/METADATA
rsacrack-1.0.1.dist-info/WHEEL
rsacrack-1.0.1.dist-info/top_level.txt
rsacrack-1.0.1.dist-info/RECORD
